gpt4all/__init__.py
gpt4all/_pyllmodel.py
gpt4all/gpt4all.py
gpt4all/llmodel_DO_NOT_MODIFY/acl_tensor.h
gpt4all/llmodel_DO_NOT_MODIFY/aclnn_ops.h
gpt4all/llmodel_DO_NOT_MODIFY/ascendc_kernels.h
gpt4all/llmodel_DO_NOT_MODIFY/clip.h
gpt4all/llmodel_DO_NOT_MODIFY/common.h
gpt4all/llmodel_DO_NOT_MODIFY/console.h
gpt4all/llmodel_DO_NOT_MODIFY/dlhandle.h
gpt4all/llmodel_DO_NOT_MODIFY/get-model.h
gpt4all/llmodel_DO_NOT_MODIFY/ggml-aarch64.h
gpt4all/llmodel_DO_NOT_MODIFY/ggml-alloc.h
gpt4all/llmodel_DO_NOT_MODIFY/ggml-backend-impl.h
gpt4all/llmodel_DO_NOT_MODIFY/ggml-backend.h
gpt4all/llmodel_DO_NOT_MODIFY/ggml-blas.h
gpt4all/llmodel_DO_NOT_MODIFY/ggml-cann.h
gpt4all/llmodel_DO_NOT_MODIFY/ggml-common.h
gpt4all/llmodel_DO_NOT_MODIFY/ggml-cuda.h
gpt4all/llmodel_DO_NOT_MODIFY/ggml-impl.h
gpt4all/llmodel_DO_NOT_MODIFY/ggml-kompute.h
gpt4all/llmodel_DO_NOT_MODIFY/ggml-metal.h
gpt4all/llmodel_DO_NOT_MODIFY/ggml-quants.h
gpt4all/llmodel_DO_NOT_MODIFY/ggml-rpc.h
gpt4all/llmodel_DO_NOT_MODIFY/ggml-sycl.h
gpt4all/llmodel_DO_NOT_MODIFY/ggml-vulkan.h
gpt4all/llmodel_DO_NOT_MODIFY/ggml.h
gpt4all/llmodel_DO_NOT_MODIFY/grammar-parser.h
gpt4all/llmodel_DO_NOT_MODIFY/httplib.h
gpt4all/llmodel_DO_NOT_MODIFY/json-schema-to-grammar.h
gpt4all/llmodel_DO_NOT_MODIFY/llama.h
gpt4all/llmodel_DO_NOT_MODIFY/llamamodel_impl.h
gpt4all/llmodel_DO_NOT_MODIFY/llava.h
gpt4all/llmodel_DO_NOT_MODIFY/llmodel.h
gpt4all/llmodel_DO_NOT_MODIFY/llmodel_c.h
gpt4all/llmodel_DO_NOT_MODIFY/llmodel_shared.h
gpt4all/llmodel_DO_NOT_MODIFY/log.h
gpt4all/llmodel_DO_NOT_MODIFY/ngram-cache.h
gpt4all/llmodel_DO_NOT_MODIFY/rotate-bits.h
gpt4all/llmodel_DO_NOT_MODIFY/sampling.h
gpt4all/llmodel_DO_NOT_MODIFY/sgemm.h
gpt4all/llmodel_DO_NOT_MODIFY/sha1.h
gpt4all/llmodel_DO_NOT_MODIFY/sha256.h
gpt4all/llmodel_DO_NOT_MODIFY/stb_image.h
gpt4all/llmodel_DO_NOT_MODIFY/sysinfo.h
gpt4all/llmodel_DO_NOT_MODIFY/train.h
gpt4all/llmodel_DO_NOT_MODIFY/unicode-data.h
gpt4all/llmodel_DO_NOT_MODIFY/unicode.h
gpt4all-2.8.1.dist-info/LICENSE.txt
gpt4all-2.8.1.dist-info/METADATA
gpt4all-2.8.1.dist-info/WHEEL
gpt4all-2.8.1.dist-info/top_level.txt
gpt4all-2.8.1.dist-info/RECORD
