Metadata-Version: 2.1
Name: gpt4all
Version: 2.8.1
Summary: Python bindings for GPT4All
Home-page: https://gpt4all.io/
Author: Nomic and the Open Source Community
Author-email: support@nomic.ai
Project-URL: Documentation, https://docs.gpt4all.io/gpt4all_python.html
Project-URL: Source code, https://github.com/nomic-ai/gpt4all/tree/main/gpt4all-bindings/python
Classifier: Programming Language :: Python :: 3
Classifier: License :: OSI Approved :: MIT License
Classifier: Operating System :: OS Independent
Requires-Python: >=3.8
License-File: LICENSE.txt
Requires-Dist: requests
Requires-Dist: tqdm
Requires-Dist: importlib-resources ; python_version < "3.9"
Requires-Dist: typing-extensions >=4.3.0 ; python_version >= "3.9" and python_version < "3.11"
Provides-Extra: all
Requires-Dist: gpt4all[cuda] ; (platform_system == "Windows" or platform_system == "Linux") and extra == 'all'
Provides-Extra: cuda
Requires-Dist: nvidia-cuda-runtime-cu11 ; extra == 'cuda'
Requires-Dist: nvidia-cublas-cu11 ; extra == 'cuda'
Provides-Extra: dev
Requires-Dist: gpt4all[all] ; extra == 'dev'
Requires-Dist: pytest ; extra == 'dev'
Requires-Dist: twine ; extra == 'dev'
Requires-Dist: wheel ; extra == 'dev'
Requires-Dist: setuptools ; extra == 'dev'
Requires-Dist: mkdocs-material ; extra == 'dev'
Requires-Dist: mkdocs-material[imaging] ; extra == 'dev'
Requires-Dist: mkautodoc ; extra == 'dev'
Requires-Dist: mkdocstrings[python] ; extra == 'dev'
Requires-Dist: mkdocs-jupyter ; extra == 'dev'
Requires-Dist: black ; extra == 'dev'
Requires-Dist: isort ; extra == 'dev'
Requires-Dist: typing-extensions >=3.10 ; extra == 'dev'
